matrics_calculator/MAE.py
matrics_calculator/MAPE.py
matrics_calculator/MSE.py
matrics_calculator/__init__.py
matrics_calculator/r2.py
matrics_calculator-3.2.3.dist-info/LICENSE
matrics_calculator-3.2.3.dist-info/METADATA
matrics_calculator-3.2.3.dist-info/WHEEL
matrics_calculator-3.2.3.dist-info/RECORD
