Metadata-Version: 2.3
Name: matrics_calculator
Version: 3.2.3
Summary: A package providing functions to calculate key regression metrics: R-squared, Mean Absolute Error (MAE), Mean Squared Error (MSE), and Mean Absolute Percentage Error (MAPE).
License: MIT
Author: Celine Habashy, Jay Mangat, Yajing Liu, Zhiwei Zhang
Requires-Python: >=3.10,<4.0
Classifier: License :: OSI Approved :: MIT License
Classifier: Programming Language :: Python :: 3
Classifier: Programming Language :: Python :: 3.10
Classifier: Programming Language :: Python :: 3.11
Classifier: Programming Language :: Python :: 3.12
Classifier: Programming Language :: Python :: 3.13
Requires-Dist: scikit-learn (>=1.6.1,<2.0.0)
